{
  "id": 187063758389248,
  "template_name": "REGESTA",
  "remark": "REGESTA测试",
  "invoicing_id": 103668833517569,
  "invoicing_keywords": "REGESTA",
  "billto_id1": 108969202417664,
  "billto_keywords1": "EASYSENT HOLDING EUROPE",
  "billto_id2": 109148475424768,
  "billto_keywords2": "GOBLIN NETHERLANDS B.V.",
  "billto_id3": 187047129874432,
  "billto_keywords3": "SUNBIRD LOGISTICS B.V.",
  "version": 33,
  "insert_user_id": 43910611042304,
  "update_user_id": 43910611042304,
  "insert_timestamp": "2023-10-30 09:29:10.443",
  "update_timestamp": "2023-12-21 10:57:10.117",
  "due_date_keywords": "Data wystawienia",
  "invoice_date_replace_char": null,
  "amount_keywords": "Razem do zapłaty:",
  "invoice_no_end": "23",
  "invoice_date_format": "yyyy-MM-dd",
  "invoice_date_offset_lines": null,
  "amount_replace_char": ",",
  "amount_begin": "1",
  "due_date_replace_char": null,
  "currency": "EUR",
  "due_date_end": "28",
  "invoice_date_begin": "45",
  "invoice_no_replace_char": null,
  "due_date_format": "yyyy-MM-dd",
  "amount_end": " EUR",
  "invoice_no_begin": "8",
  "due_date_begin": "18",
  "payment_days": null,
  "amount_offset_lines": "2",
  "invoice_date_end": "55",
  "invoice_no_offset_lines": null,
  "due_date_offset_lines": null,
  "invoice_no_keywords": "FAKTURA",
  "invoice_date_keywords": "Data sprzedaży",
  "invoicing_coc_type": "servprov",
  "invoicing_company_name": "Regesta",
  "billto_company_name1": "EASYSENT HOLDING EUROPE",
  "billto_company_name2": "Goblin4434",
  "billto_company_name3": "Sunbird Logistics B.V.",
  "shipment_end": null,
  "detail_amount_keywords": null,
  "shipment_begin": null,
  "detail_amount_replace_char": ",",
  "departure_date_replace_char": null,
  "detail_amount_end": "11",
  "detail_amount_begin": "3",
  "container_replace_char": null,
  "match_detail_method": "CONTAINER,SHIPMENT",
  "shipment_keywords": null,
  "detail_amount_offset_lines": "4",
  "container_offset_lines": null,
  "shipment_offset_lines": null,
  "departure_date_offset_lines": "3",
  "departure_date_begin": "17",
  "container_end": null,
  "container_keywords": null,
  "shipment_replace_char": null,
  "container_begin": "16",
  "departure_date_end": "26",
  "departure_date_keywords": null,
  "departure_date_format": "yyyy-MM-dd",
  "billto_vat1": 0.0000,
  "billto_vat2": 0.0000,
  "billto_vat3": 0.0000,
  "auto_remove": "0",
  "bac_replace_char": null,
  "bac_begin": "SWIFT: SWIFT:",
  "iban_end": "35",
  "iban_replace_char": " ",
  "bac_keywords": "SWIFT: SWIFT:",
  "bac_offset_lines": null,
  "iban_keywords": "Numer rachunku:",
  "iban_offset_lines": "4",
  "bac_end": "21",
  "iban_begin": "1"
}